gitself/__init__.py
gitself/templates.py
gitself/vendored/__init__.py
gitself/vendored/pushid.py
gitself-25.8.0b1.dist-info/METADATA
gitself-25.8.0b1.dist-info/WHEEL
gitself-25.8.0b1.dist-info/entry_points.txt
gitself-25.8.0b1.dist-info/RECORD
