Metadata-Version: 2.4
Name: gitself
Version: 25.8.0b1
Summary: Gitself, for those who are tired of those other code forges.
Author-email: Wayne Werner <wayne@waynewerner.com>
Requires-Python: >=3.13
